PyUtauCli/PyUtauCli.py
PyUtauCli/__init__.py
PyUtauCli/common/__init__.py
PyUtauCli/common/convert_notenum.py
PyUtauCli/projects/Entry.py
PyUtauCli/projects/EntryBase.py
PyUtauCli/projects/Note.py
PyUtauCli/projects/Render.py
PyUtauCli/projects/RenderNote.py
PyUtauCli/projects/Ust.py
PyUtauCli/projects/UtauPlugin.py
PyUtauCli/projects/__init__.py
PyUtauCli/settings/__init__.py
PyUtauCli/settings/logger.py
PyUtauCli/settings/settings.py
PyUtauCli/settings/win_utau.py
PyUtauCli/voicebank/__init__.py
PyUtauCli/voicebank/character.py
PyUtauCli/voicebank/frq.py
PyUtauCli/voicebank/oto.py
PyUtauCli/voicebank/prefixmap.py
PyUtauCli/voicebank/voicebank.py
PyUtauCli-0.0.2.dist-info/LICENSE
PyUtauCli-0.0.2.dist-info/METADATA
PyUtauCli-0.0.2.dist-info/WHEEL
PyUtauCli-0.0.2.dist-info/top_level.txt
PyUtauCli-0.0.2.dist-info/RECORD
