Metadata-Version: 2.1
Name: PyUtauCli
Version: 0.0.2
Summary: UTAU's command client
Home-page: https://github.com/delta-kimigatame/PyUtauCli
Author: delta_kimigatame
Author-email: sankaku.kuro@gmail.com
Project-URL: Bug Tracker, https://github.com/delta-kimigatame/PyUtauCli/issues
Classifier: Programming Language :: Python :: 3
Classifier: License :: OSI Approved :: MIT License
Classifier: Operating System :: OS Independent
Requires-Python: >=3.7
License-File: LICENSE
Requires-Dist: numpy
Requires-Dist: PyRwu
Requires-Dist: PyWavTool
